[
  {
    "content": "New $49 quick teardown: one AI workflow, restaurant call flow, n8n automation, or agent ha",
    "status": "published",
    "platforms": [
      {
        "platform": "bluesky",
        "status": "published",
        "publishedAt": "2026-05-06T19:02:33.214Z",
        "platformPostUrl": "https://bsky.app/profile/iganapolsky.bsky.social/post/3ml7fba5ee42l"
      }
    ]
  },
  {
    "content": "I added the low-friction version: $49 AI Workflow Quick Teardown. Send one broken workflow",
    "status": "published",
    "platforms": [
      {
        "platform": "threads",
        "status": "published",
        "publishedAt": "2026-05-06T19:02:27.874Z",
        "platformPostUrl": "https://www.threads.com/@igorganapolsky/post/DYAhq0VlJAt"
      }
    ]
  }
]
